CHANGES.txt
LICENSE.txt
README.txt
setup.py
js/__init__.py
js.javascript_canvas_to_blob.egg-info/PKG-INFO
js.javascript_canvas_to_blob.egg-info/SOURCES.txt
js.javascript_canvas_to_blob.egg-info/dependency_links.txt
js.javascript_canvas_to_blob.egg-info/entry_points.txt
js.javascript_canvas_to_blob.egg-info/namespace_packages.txt
js.javascript_canvas_to_blob.egg-info/not-zip-safe
js.javascript_canvas_to_blob.egg-info/requires.txt
js.javascript_canvas_to_blob.egg-info/top_level.txt
js/javascript_canvas_to_blob/__init__.py
js/javascript_canvas_to_blob/test_javascript_canvas_to_blob.txt
js/javascript_canvas_to_blob/resources/canvas-to-blob.js
js/javascript_canvas_to_blob/resources/canvas-to-blob.min.js