Metadata-Version: 1.0
Name: js.javascript-canvas-to-blob
Version: 2.0.5
Summary: Fanstatic packaging of JavaScript Canvas to Blob
Home-page: https://github.com/disko/js.javascript_canvas_to_blob
Author: Andreas Kaiser
Author-email: disko@binary-punks.com
License: BSD
Platform: UNKNOWN
